setup.py
namegen/__init__.py
namegen/namegen.py
namegen/names.py
namegen.egg-info/PKG-INFO
namegen.egg-info/SOURCES.txt
namegen.egg-info/dependency_links.txt
namegen.egg-info/namespace_packages.txt
namegen.egg-info/top_level.txt