Metadata-Version: 1.0
Name: namegen
Version: 1.0.0
Summary: Name Generator
Home-page: https://github.com/amnong/namegen
Author: Amnon Grossman
Author-email: emesh1@gmail.com
License: BSD
Platform: UNKNOWN
Classifier: Development Status :: 5 - Production/Stable
Classifier: Intended Audience :: Developers
Classifier: Programming Language :: Python :: 2.7
